androidautotest/__init__.py
androidautotest/__main__.py
androidautotest/api.py
androidautotest/client.py
androidautotest/errors.py
androidautotest/logger.py
androidautotest/tool.py
androidautotest-0.0.2.33.dist-info/LICENSE
androidautotest-0.0.2.33.dist-info/METADATA
androidautotest-0.0.2.33.dist-info/WHEEL
androidautotest-0.0.2.33.dist-info/top_level.txt
androidautotest-0.0.2.33.dist-info/RECORD
