Metadata-Version: 2.1
Name: androidautotest
Version: 0.0.2.33
Summary: android test framework using adb connection and template matching in opencv
Home-page: https://github.com/15045120/AndroidTest
Author: 15045120
Author-email: 1337078409@qq.com
License: UNKNOWN
Platform: UNKNOWN
Classifier: Programming Language :: Python :: 3
Classifier: License :: OSI Approved :: MIT License
Classifier: Operating System :: OS Independent
Requires-Python: >=3.5
Requires-Dist: psutil
Requires-Dist: pillow
Requires-Dist: numpy
Requires-Dist: opencv-python
